{
"instructions_readme": "1) Open Chrome, 2) go to chrome://tracing, 3) click Load, 4) navigate to this file.",

"traceEvents":[
{ "pid": 1, "tid": 1, "ph": "M", "name": "thread_name", "args": { "name": "" } },
{ "pid": 1, "tid": 1, "ts": 60.9, "dur": 37143881.6, "ph": "X", "name": "il2cpp.exe", "args": { "durationMS": 37143.8816, "detail": "" } },
{ "pid": 1, "tid": 1, "ts": 15968.7, "dur": 37127974.4, "ph": "X", "name": "ConvertAssemblies", "args": { "durationMS": 37127.9744, "detail": "" } },
{ "pid": 1, "tid": 1, "ts": 39963.3, "dur": 94626.5, "ph": "X", "name": "Collect assemblies to convert", "args": { "durationMS": 94.6265, "detail": "" } },
{ "pid": 1, "tid": 1, "ts": 134939.5, "dur": 38500, "ph": "X", "name": "RegisterCorlib", "args": { "durationMS": 38.5, "detail": "" } },
{ "pid": 1, "tid": 1, "ts": 173592.1, "dur": 77964.5, "ph": "X", "name": "PreProcessIL", "args": { "durationMS": 77.9645, "detail": "" } },
{ "pid": 1, "tid": 1, "ts": 173593.3, "dur": 10287, "ph": "X", "name": "Inject base types and finalizers into COM and Windows Runtime types", "args": { "durationMS": 10.287, "detail": "" } },
{ "pid": 1, "tid": 1, "ts": 173789.3, "dur": 6280.7, "ph": "X", "name": "ModifyCOMAndWindowsRuntimeTypes in assembly", "args": { "durationMS": 6.2807, "detail": "mscorlib" } },
{ "pid": 1, "tid": 1, "ts": 180327.7, "dur": 675.4, "ph": "X", "name": "ModifyCOMAndWindowsRuntimeTypes in assembly", "args": { "durationMS": 0.6754, "detail": "System.Xml" } },
{ "pid": 1, "tid": 1, "ts": 181003.5, "dur": 650.7, "ph": "X", "name": "ModifyCOMAndWindowsRuntimeTypes in assembly", "args": { "durationMS": 0.6507, "detail": "System" } },
{ "pid": 1, "tid": 1, "ts": 182156, "dur": 591.8, "ph": "X", "name": "ModifyCOMAndWindowsRuntimeTypes in assembly", "args": { "durationMS": 0.5918, "detail": "UnityEngine.UI" } },
{ "pid": 1, "tid": 1, "ts": 183264.4, "dur": 379.2, "ph": "X", "name": "ModifyCOMAndWindowsRuntimeTypes in assembly", "args": { "durationMS": 0.3792, "detail": "Assembly-CSharp-firstpass" } },
{ "pid": 1, "tid": 1, "ts": 183883.4, "dur": 67673, "ph": "X", "name": "ApplyDefaultMarshalAsAttribute", "args": { "durationMS": 67.673, "detail": "" } },
{ "pid": 1, "tid": 1, "ts": 184049.3, "dur": 27864.2, "ph": "X", "name": "ApplyDefaultMarshalAsAttributeVisitor in assembly", "args": { "durationMS": 27.8642, "detail": "mscorlib" } },
{ "pid": 1, "tid": 1, "ts": 211975.3, "dur": 494.6, "ph": "X", "name": "ApplyDefaultMarshalAsAttributeVisitor in assembly", "args": { "durationMS": 0.4946, "detail": "Mono.Security" } },
{ "pid": 1, "tid": 1, "ts": 212470.3, "dur": 14272.5, "ph": "X", "name": "ApplyDefaultMarshalAsAttributeVisitor in assembly", "args": { "durationMS": 14.2725, "detail": "System.Xml" } },
{ "pid": 1, "tid": 1, "ts": 226744.1, "dur": 3816.4, "ph": "X", "name": "ApplyDefaultMarshalAsAttributeVisitor in assembly", "args": { "durationMS": 3.8164, "detail": "System" } },
{ "pid": 1, "tid": 1, "ts": 230561.8, "dur": 4967.7, "ph": "X", "name": "ApplyDefaultMarshalAsAttributeVisitor in assembly", "args": { "durationMS": 4.9677, "detail": "System.Core" } },
{ "pid": 1, "tid": 1, "ts": 235639.5, "dur": 2240.7, "ph": "X", "name": "ApplyDefaultMarshalAsAttributeVisitor in assembly", "args": { "durationMS": 2.2407, "detail": "UnityEngine.CoreModule" } },
{ "pid": 1, "tid": 1, "ts": 238435.9, "dur": 557.2, "ph": "X", "name": "ApplyDefaultMarshalAsAttributeVisitor in assembly", "args": { "durationMS": 0.5572, "detail": "UnityEngine.IMGUIModule" } },
{ "pid": 1, "tid": 1, "ts": 239375.2, "dur": 1593.8, "ph": "X", "name": "ApplyDefaultMarshalAsAttributeVisitor in assembly", "args": { "durationMS": 1.5938, "detail": "UnityEngine.UI" } },
{ "pid": 1, "tid": 1, "ts": 241003.1, "dur": 6441, "ph": "X", "name": "ApplyDefaultMarshalAsAttributeVisitor in assembly", "args": { "durationMS": 6.441, "detail": "Unity.TextMeshPro" } },
{ "pid": 1, "tid": 1, "ts": 247445.2, "dur": 1040.2, "ph": "X", "name": "ApplyDefaultMarshalAsAttributeVisitor in assembly", "args": { "durationMS": 1.0402, "detail": "UnityEngine.GameCenterModule" } },
{ "pid": 1, "tid": 1, "ts": 248504.7, "dur": 1158.5, "ph": "X", "name": "ApplyDefaultMarshalAsAttributeVisitor in assembly", "args": { "durationMS": 1.1585, "detail": "Unity.VectorGraphics" } },
{ "pid": 1, "tid": 1, "ts": 249674.4, "dur": 1329.8, "ph": "X", "name": "ApplyDefaultMarshalAsAttributeVisitor in assembly", "args": { "durationMS": 1.3298, "detail": "Assembly-CSharp-firstpass" } },
{ "pid": 1, "tid": 1, "ts": 251004.6, "dur": 550.7, "ph": "X", "name": "ApplyDefaultMarshalAsAttributeVisitor in assembly", "args": { "durationMS": 0.5507, "detail": "Assembly-CSharp" } },
{ "pid": 1, "tid": 1, "ts": 251703.2, "dur": 6671.2, "ph": "X", "name": "WriteResources", "args": { "durationMS": 6.6712, "detail": "" } },
{ "pid": 1, "tid": 1, "ts": 258516.6, "dur": 37577.8, "ph": "X", "name": "CopyEtcFolder", "args": { "durationMS": 37.5778, "detail": "" } },
{ "pid": 1, "tid": 1, "ts": 296804.4, "dur": 461268.3, "ph": "X", "name": "PreProcessStage", "args": { "durationMS": 461.2683, "detail": "" } },
{ "pid": 1, "tid": 1, "ts": 758803.3, "dur": 1288.6, "ph": "X", "name": "Debugger Sequence Points", "args": { "durationMS": 1.2886, "detail": "" } },
{ "pid": 1, "tid": 1, "ts": 760891.2, "dur": 2893321, "ph": "X", "name": "Generics Collection", "args": { "durationMS": 2893.321, "detail": "" } },
{ "pid": 1, "tid": 1, "ts": 760892.4, "dur": 2813635.4, "ph": "X", "name": "GenericsCollector.Collect", "args": { "durationMS": 2813.6354, "detail": "" } },
{ "pid": 1, "tid": 1, "ts": 761577.3, "dur": 21213.2, "ph": "X", "name": "GenericCodeFlowGraphCollector.Collect", "args": { "durationMS": 21.2132, "detail": "" } },
{ "pid": 1, "tid": 1, "ts": 761578.6, "dur": 20374.6, "ph": "X", "name": "GenericCodeFlowGraphCollector.GetTypesAndMethodsForAnalysis", "args": { "durationMS": 20.3746, "detail": "" } },
{ "pid": 1, "tid": 1, "ts": 3574536.8, "dur": 78675.3, "ph": "X", "name": "CollectGenericVirtualMethods.Collect", "args": { "durationMS": 78.6753, "detail": "" } },
{ "pid": 1, "tid": 1, "ts": 3653216, "dur": 775.4, "ph": "X", "name": "AddExtraTypes", "args": { "durationMS": 0.7754, "detail": "" } },
{ "pid": 1, "tid": 1, "ts": 3654213.6, "dur": 1902.6, "ph": "X", "name": "Add Windows Runtime type names", "args": { "durationMS": 1.9026, "detail": "" } },
{ "pid": 1, "tid": 1, "ts": 3656809.6, "dur": 19583459.2, "ph": "X", "name": "AllAssemblyConversion", "args": { "durationMS": 19583.4592, "detail": "" } },
{ "pid": 1, "tid": 1, "ts": 3657420, "dur": 6000379.2, "ph": "X", "name": "Convert assembly non-generic methods", "args": { "durationMS": 6000.3792, "detail": "mscorlib" } },
{ "pid": 1, "tid": 1, "ts": 9657802.4, "dur": 16256.4, "ph": "X", "name": "Convert assembly non-generic methods", "args": { "durationMS": 16.2564, "detail": "System.Configuration" } },
{ "pid": 1, "tid": 1, "ts": 9674061.6, "dur": 353590.5, "ph": "X", "name": "Convert assembly non-generic methods", "args": { "durationMS": 353.5905, "detail": "Mono.Security" } },
{ "pid": 1, "tid": 1, "ts": 10027654.4, "dur": 3637993.2, "ph": "X", "name": "Convert assembly non-generic methods", "args": { "durationMS": 3637.9932, "detail": "System.Xml" } },
{ "pid": 1, "tid": 1, "ts": 13665649.6, "dur": 2084220.2, "ph": "X", "name": "Convert assembly non-generic methods", "args": { "durationMS": 2084.2202, "detail": "System" } },
{ "pid": 1, "tid": 1, "ts": 15749872, "dur": 40916.9, "ph": "X", "name": "Convert assembly non-generic methods", "args": { "durationMS": 40.9169, "detail": "System.Core" } },
{ "pid": 1, "tid": 1, "ts": 15790792, "dur": 17546.3, "ph": "X", "name": "Convert assembly non-generic methods", "args": { "durationMS": 17.5463, "detail": "UnityEngine.SharedInternalsModule" } },
{ "pid": 1, "tid": 1, "ts": 15808339.2, "dur": 749185.6, "ph": "X", "name": "Convert assembly non-generic methods", "args": { "durationMS": 749.1856, "detail": "UnityEngine.CoreModule" } },
{ "pid": 1, "tid": 1, "ts": 16557526.4, "dur": 6085.4, "ph": "X", "name": "Convert assembly non-generic methods", "args": { "durationMS": 6.0854, "detail": "UnityEngine.AssetBundleModule" } },
{ "pid": 1, "tid": 1, "ts": 16563614.4, "dur": 986.1, "ph": "X", "name": "Convert assembly non-generic methods", "args": { "durationMS": 0.9861, "detail": "UnityEngine.GridModule" } },
{ "pid": 1, "tid": 1, "ts": 16564601.6, "dur": 20881, "ph": "X", "name": "Convert assembly non-generic methods", "args": { "durationMS": 20.881, "detail": "UnityEngine.InputLegacyModule" } },
{ "pid": 1, "tid": 1, "ts": 16585486.4, "dur": 4466.7, "ph": "X", "name": "Convert assembly non-generic methods", "args": { "durationMS": 4.4667, "detail": "UnityEngine.Physics2DModule" } },
{ "pid": 1, "tid": 1, "ts": 16589953.6, "dur": 26439.8, "ph": "X", "name": "Convert assembly non-generic methods", "args": { "durationMS": 26.4398, "detail": "UnityEngine.TextRenderingModule" } },
{ "pid": 1, "tid": 1, "ts": 16616395.2, "dur": 53294.8, "ph": "X", "name": "Convert assembly non-generic methods", "args": { "durationMS": 53.2948, "detail": "UnityEngine.UnityWebRequestModule" } },
{ "pid": 1, "tid": 1, "ts": 16669692.8, "dur": 34702.7, "ph": "X", "name": "Convert assembly non-generic methods", "args": { "durationMS": 34.7027, "detail": "UnityEngine.AnimationModule" } },
{ "pid": 1, "tid": 1, "ts": 16704396.8, "dur": 10647.4, "ph": "X", "name": "Convert assembly non-generic methods", "args": { "durationMS": 10.6474, "detail": "UnityEngine.AudioModule" } },
{ "pid": 1, "tid": 1, "ts": 16715046.4, "dur": 341663.8, "ph": "X", "name": "Convert assembly non-generic methods", "args": { "durationMS": 341.6638, "detail": "UnityEngine.IMGUIModule" } },
{ "pid": 1, "tid": 1, "ts": 17056712, "dur": 1743.3, "ph": "X", "name": "Convert assembly non-generic methods", "args": { "durationMS": 1.7433, "detail": "UnityEngine.ImageConversionModule" } },
{ "pid": 1, "tid": 1, "ts": 17058456, "dur": 29729.4, "ph": "X", "name": "Convert assembly non-generic methods", "args": { "durationMS": 29.7294, "detail": "UnityEngine.PhysicsModule" } },
{ "pid": 1, "tid": 1, "ts": 17088188.8, "dur": 995.6, "ph": "X", "name": "Convert assembly non-generic methods", "args": { "durationMS": 0.9956, "detail": "UnityEngine.SpriteShapeModule" } },
{ "pid": 1, "tid": 1, "ts": 17089187.2, "dur": 1063.1, "ph": "X", "name": "Convert assembly non-generic methods", "args": { "durationMS": 1.0631, "detail": "UnityEngine.TilemapModule" } },
{ "pid": 1, "tid": 1, "ts": 17090252.8, "dur": 26029.6, "ph": "X", "name": "Convert assembly non-generic methods", "args": { "durationMS": 26.0296, "detail": "UnityEngine.UIModule" } },
{ "pid": 1, "tid": 1, "ts": 17116284.8, "dur": 5240.7, "ph": "X", "name": "Convert assembly non-generic methods", "args": { "durationMS": 5.2407, "detail": "UnityEngine.UnityWebRequestAssetBundleModule" } },
{ "pid": 1, "tid": 1, "ts": 17121526.4, "dur": 55511.1, "ph": "X", "name": "Convert assembly non-generic methods", "args": { "durationMS": 55.5111, "detail": "UnityEngine.TextCoreModule" } },
{ "pid": 1, "tid": 1, "ts": 17177040, "dur": 1257033.6, "ph": "X", "name": "Convert assembly non-generic methods", "args": { "durationMS": 1257.0336, "detail": "UnityEngine.UI" } },
{ "pid": 1, "tid": 1, "ts": 18434075.2, "dur": 10156.2, "ph": "X", "name": "Convert assembly non-generic methods", "args": { "durationMS": 10.1562, "detail": "UnityEngine.UnityWebRequestWWWModule" } },
{ "pid": 1, "tid": 1, "ts": 18444233.6, "dur": 2429578.4, "ph": "X", "name": "Convert assembly non-generic methods", "args": { "durationMS": 2429.5784, "detail": "Unity.TextMeshPro" } },
{ "pid": 1, "tid": 1, "ts": 20873814.4, "dur": 57717.2, "ph": "X", "name": "Convert assembly non-generic methods", "args": { "durationMS": 57.7172, "detail": "UnityEngine.GameCenterModule" } },
{ "pid": 1, "tid": 1, "ts": 20931532.8, "dur": 1150.5, "ph": "X", "name": "Convert assembly non-generic methods", "args": { "durationMS": 1.1505, "detail": "UnityEngine.ScreenCaptureModule" } },
{ "pid": 1, "tid": 1, "ts": 20932684.8, "dur": 1081983.7, "ph": "X", "name": "Convert assembly non-generic methods", "args": { "durationMS": 1081.9837, "detail": "Unity.VectorGraphics" } },
{ "pid": 1, "tid": 1, "ts": 22014670.4, "dur": 579.1, "ph": "X", "name": "Convert assembly non-generic methods", "args": { "durationMS": 0.5791, "detail": "UnityEngine" } },
{ "pid": 1, "tid": 1, "ts": 22015251.2, "dur": 800431.4, "ph": "X", "name": "Convert assembly non-generic methods", "args": { "durationMS": 800.4314, "detail": "Assembly-CSharp-firstpass" } },
{ "pid": 1, "tid": 1, "ts": 22815683.2, "dur": 424584.5, "ph": "X", "name": "Convert assembly non-generic methods", "args": { "durationMS": 424.5845, "detail": "Assembly-CSharp" } },
{ "pid": 1, "tid": 1, "ts": 23240440, "dur": 8861202.4, "ph": "X", "name": "WriteGenerics", "args": { "durationMS": 8861.2024, "detail": "" } },
{ "pid": 1, "tid": 1, "ts": 23241888, "dur": 1622612.6, "ph": "X", "name": "GenericInstanceMethods", "args": { "durationMS": 1622.6126, "detail": "" } },
{ "pid": 1, "tid": 1, "ts": 24864507.2, "dur": 6681954.8, "ph": "X", "name": "GenericInstanceTypes", "args": { "durationMS": 6681.9548, "detail": "" } },
{ "pid": 1, "tid": 1, "ts": 31546588.8, "dur": 555022.2, "ph": "X", "name": "GenericComDefinitions", "args": { "durationMS": 555.0222, "detail": "" } },
{ "pid": 1, "tid": 1, "ts": 32101894.4, "dur": 613.5, "ph": "X", "name": "Executable Processing", "args": { "durationMS": 0.6135, "detail": "" } },
{ "pid": 1, "tid": 1, "ts": 32102816, "dur": 593522.2, "ph": "X", "name": "MetadataCollector", "args": { "durationMS": 593.5222, "detail": "" } },
{ "pid": 1, "tid": 1, "ts": 32105344, "dur": 13875.9, "ph": "X", "name": "UpdateEmptyTokens", "args": { "durationMS": 13.8759, "detail": "" } },
{ "pid": 1, "tid": 1, "ts": 32119840, "dur": 17353, "ph": "X", "name": "ValidateTokens", "args": { "durationMS": 17.353, "detail": "" } },
{ "pid": 1, "tid": 1, "ts": 32696777.6, "dur": 1837.5, "ph": "X", "name": "Write COM Callable Wrappers", "args": { "durationMS": 1.8375, "detail": "" } },
{ "pid": 1, "tid": 1, "ts": 32698704, "dur": 500.1, "ph": "X", "name": "Write Windows Runtime Factories", "args": { "durationMS": 0.5001, "detail": "" } },
{ "pid": 1, "tid": 1, "ts": 32699500.8, "dur": 4442732.4, "ph": "X", "name": "Metadata", "args": { "durationMS": 4442.7324, "detail": "Global" } },
{ "pid": 1, "tid": 1, "ts": 32813827.2, "dur": 1326758.5, "ph": "X", "name": "Il2CppAttributes.cpp", "args": { "durationMS": 1326.7585, "detail": "" } },
{ "pid": 1, "tid": 1, "ts": 34473257.6, "dur": 24541.3, "ph": "X", "name": "UnresolvedVirtualCallStubs.cpp", "args": { "durationMS": 24.5413, "detail": "" } },
{ "pid": 1, "tid": 1, "ts": 34502406.4, "dur": 702330.4, "ph": "X", "name": "WriteCodeRegistration", "args": { "durationMS": 702.3304, "detail": "" } },
{ "pid": 1, "tid": 1, "ts": 34502451.2, "dur": 120821.7, "ph": "X", "name": "mscorlib_CodeGen.c", "args": { "durationMS": 120.8217, "detail": "" } },
{ "pid": 1, "tid": 1, "ts": 34609568, "dur": 3956.6, "ph": "X", "name": "GenericContextCollector", "args": { "durationMS": 3.9566, "detail": "Collect" } },
{ "pid": 1, "tid": 1, "ts": 34623296, "dur": 790.1, "ph": "X", "name": "System.Configuration_CodeGen.c", "args": { "durationMS": 0.7901, "detail": "" } },
{ "pid": 1, "tid": 1, "ts": 34624099.2, "dur": 4778.2, "ph": "X", "name": "Mono.Security_CodeGen.c", "args": { "durationMS": 4.7782, "detail": "" } },
{ "pid": 1, "tid": 1, "ts": 34628896, "dur": 54065.2, "ph": "X", "name": "System.Xml_CodeGen.c", "args": { "durationMS": 54.0652, "detail": "" } },
{ "pid": 1, "tid": 1, "ts": 34682985.6, "dur": 31199.8, "ph": "X", "name": "System_CodeGen.c", "args": { "durationMS": 31.1998, "detail": "" } },
{ "pid": 1, "tid": 1, "ts": 34711353.6, "dur": 449.5, "ph": "X", "name": "GenericContextCollector", "args": { "durationMS": 0.4495, "detail": "Collect" } },
{ "pid": 1, "tid": 1, "ts": 34714204.8, "dur": 2331.4, "ph": "X", "name": "System.Core_CodeGen.c", "args": { "durationMS": 2.3314, "detail": "" } },
{ "pid": 1, "tid": 1, "ts": 34715392, "dur": 407.8, "ph": "X", "name": "GenericContextCollector", "args": { "durationMS": 0.4078, "detail": "Collect" } },
{ "pid": 1, "tid": 1, "ts": 34716544, "dur": 923.3, "ph": "X", "name": "UnityEngine.SharedInternalsModule_CodeGen.c", "args": { "durationMS": 0.9233, "detail": "" } },
{ "pid": 1, "tid": 1, "ts": 34717478.4, "dur": 19996.8, "ph": "X", "name": "UnityEngine.CoreModule_CodeGen.c", "args": { "durationMS": 19.9968, "detail": "" } },
{ "pid": 1, "tid": 1, "ts": 34735001.6, "dur": 475.7, "ph": "X", "name": "GenericContextCollector", "args": { "durationMS": 0.4757, "detail": "Collect" } },
{ "pid": 1, "tid": 1, "ts": 34737491.2, "dur": 676.1, "ph": "X", "name": "UnityEngine.AssetBundleModule_CodeGen.c", "args": { "durationMS": 0.6761, "detail": "" } },
{ "pid": 1, "tid": 1, "ts": 34738182.4, "dur": 556.2, "ph": "X", "name": "UnityEngine.GridModule_CodeGen.c", "args": { "durationMS": 0.5562, "detail": "" } },
{ "pid": 1, "tid": 1, "ts": 34738755.2, "dur": 1365.8, "ph": "X", "name": "UnityEngine.InputLegacyModule_CodeGen.c", "args": { "durationMS": 1.3658, "detail": "" } },
{ "pid": 1, "tid": 1, "ts": 34740140.8, "dur": 667.6, "ph": "X", "name": "UnityEngine.Physics2DModule_CodeGen.c", "args": { "durationMS": 0.6676, "detail": "" } },
{ "pid": 1, "tid": 1, "ts": 34740822.4, "dur": 1588.4, "ph": "X", "name": "UnityEngine.TextRenderingModule_CodeGen.c", "args": { "durationMS": 1.5884, "detail": "" } },
{ "pid": 1, "tid": 1, "ts": 34742425.6, "dur": 1330.5, "ph": "X", "name": "UnityEngine.UnityWebRequestModule_CodeGen.c", "args": { "durationMS": 1.3305, "detail": "" } },
{ "pid": 1, "tid": 1, "ts": 34743766.4, "dur": 972.6, "ph": "X", "name": "UnityEngine.AnimationModule_CodeGen.c", "args": { "durationMS": 0.9726, "detail": "" } },
{ "pid": 1, "tid": 1, "ts": 34744748.8, "dur": 1587.4, "ph": "X", "name": "UnityEngine.AudioModule_CodeGen.c", "args": { "durationMS": 1.5874, "detail": "" } },
{ "pid": 1, "tid": 1, "ts": 34746345.6, "dur": 4976.7, "ph": "X", "name": "UnityEngine.IMGUIModule_CodeGen.c", "args": { "durationMS": 4.9767, "detail": "" } },
{ "pid": 1, "tid": 1, "ts": 34751334.4, "dur": 366.5, "ph": "X", "name": "UnityEngine.ImageConversionModule_CodeGen.c", "args": { "durationMS": 0.3665, "detail": "" } },
{ "pid": 1, "tid": 1, "ts": 34751708.8, "dur": 1056.8, "ph": "X", "name": "UnityEngine.PhysicsModule_CodeGen.c", "args": { "durationMS": 1.0568, "detail": "" } },
{ "pid": 1, "tid": 1, "ts": 34753331.2, "dur": 1180.6, "ph": "X", "name": "UnityEngine.UIModule_CodeGen.c", "args": { "durationMS": 1.1806, "detail": "" } },
{ "pid": 1, "tid": 1, "ts": 34754518.4, "dur": 382, "ph": "X", "name": "UnityEngine.UnityWebRequestAssetBundleModule_CodeGen.c", "args": { "durationMS": 0.382, "detail": "" } },
{ "pid": 1, "tid": 1, "ts": 34754908.8, "dur": 1416.8, "ph": "X", "name": "UnityEngine.TextCoreModule_CodeGen.c", "args": { "durationMS": 1.4168, "detail": "" } },
{ "pid": 1, "tid": 1, "ts": 34756342.4, "dur": 14957.3, "ph": "X", "name": "UnityEngine.UI_CodeGen.c", "args": { "durationMS": 14.9573, "detail": "" } },
{ "pid": 1, "tid": 1, "ts": 34771312, "dur": 547.6, "ph": "X", "name": "UnityEngine.UnityWebRequestWWWModule_CodeGen.c", "args": { "durationMS": 0.5476, "detail": "" } },
{ "pid": 1, "tid": 1, "ts": 34771868.8, "dur": 15868.8, "ph": "X", "name": "Unity.TextMeshPro_CodeGen.c", "args": { "durationMS": 15.8688, "detail": "" } },
{ "pid": 1, "tid": 1, "ts": 34787750.4, "dur": 2060.4, "ph": "X", "name": "UnityEngine.GameCenterModule_CodeGen.c", "args": { "durationMS": 2.0604, "detail": "" } },
{ "pid": 1, "tid": 1, "ts": 34789824, "dur": 421.8, "ph": "X", "name": "UnityEngine.ScreenCaptureModule_CodeGen.c", "args": { "durationMS": 0.4218, "detail": "" } },
{ "pid": 1, "tid": 1, "ts": 34790256, "dur": 10451.8, "ph": "X", "name": "Unity.VectorGraphics_CodeGen.c", "args": { "durationMS": 10.4518, "detail": "" } },
{ "pid": 1, "tid": 1, "ts": 34801020.8, "dur": 13006, "ph": "X", "name": "Assembly-CSharp-firstpass_CodeGen.c", "args": { "durationMS": 13.006, "detail": "" } },
{ "pid": 1, "tid": 1, "ts": 34814035.2, "dur": 3993.5, "ph": "X", "name": "Assembly-CSharp_CodeGen.c", "args": { "durationMS": 3.9935, "detail": "" } },
{ "pid": 1, "tid": 1, "ts": 34818649.6, "dur": 1046.3, "ph": "X", "name": "Il2CppReversePInvokeWrapperTable.cpp", "args": { "durationMS": 1.0463, "detail": "" } },
{ "pid": 1, "tid": 1, "ts": 34819827.2, "dur": 227959.3, "ph": "X", "name": "Il2CppGenericMethodPointerTable.cpp", "args": { "durationMS": 227.9593, "detail": "" } },
{ "pid": 1, "tid": 1, "ts": 35048022.4, "dur": 130396.3, "ph": "X", "name": "Il2CppInvokerTable.cpp", "args": { "durationMS": 130.3963, "detail": "" } },
{ "pid": 1, "tid": 1, "ts": 35179456, "dur": 23061.2, "ph": "X", "name": "Il2CppInteropDataTable.cpp", "args": { "durationMS": 23.0612, "detail": "" } },
{ "pid": 1, "tid": 1, "ts": 35203984, "dur": 749.6, "ph": "X", "name": "Il2CppCodeRegistration.cpp", "args": { "durationMS": 0.7496, "detail": "" } },
{ "pid": 1, "tid": 1, "ts": 35204739.2, "dur": 1937494, "ph": "X", "name": "WriteMetadata", "args": { "durationMS": 1937.494, "detail": "" } },
{ "pid": 1, "tid": 1, "ts": 35209584, "dur": 383490.1, "ph": "X", "name": "Il2CppMetadataUsage.c", "args": { "durationMS": 383.4901, "detail": "" } },
{ "pid": 1, "tid": 1, "ts": 35348998.4, "dur": 6329.2, "ph": "X", "name": "Metadata", "args": { "durationMS": 6.3292, "detail": "Collect string literals" } },
{ "pid": 1, "tid": 1, "ts": 35617276.8, "dur": 43077.5, "ph": "X", "name": "Il2CppGenericClassTable.c", "args": { "durationMS": 43.0775, "detail": "" } },
{ "pid": 1, "tid": 1, "ts": 35660377.6, "dur": 47225.1, "ph": "X", "name": "Il2CppGenericInstDefinitions.c", "args": { "durationMS": 47.2251, "detail": "" } },
{ "pid": 1, "tid": 1, "ts": 35707628.8, "dur": 607202.9, "ph": "X", "name": "Il2CppGenericMethodTable.c", "args": { "durationMS": 607.2029, "detail": "" } },
{ "pid": 1, "tid": 1, "ts": 36314851.2, "dur": 141060.1, "ph": "X", "name": "Il2CppTypeDefinitions.c", "args": { "durationMS": 141.0601, "detail": "" } },
{ "pid": 1, "tid": 1, "ts": 36455939.2, "dur": 117292, "ph": "X", "name": "Il2CppGenericMethodDefinitions.c", "args": { "durationMS": 117.292, "detail": "" } },
{ "pid": 1, "tid": 1, "ts": 36573241.6, "dur": 242877.4, "ph": "X", "name": "CompilerCalculateTypeValues", "args": { "durationMS": 242.8774, "detail": "" } },
{ "pid": 1, "tid": 1, "ts": 36816134.4, "dur": 1618.8, "ph": "X", "name": "Il2CppMetadataRegistration.c", "args": { "durationMS": 1.6188, "detail": "" } },
{ "pid": 1, "tid": 1, "ts": 36818086.4, "dur": 8152.7, "ph": "X", "name": "StringLiteralWriter", "args": { "durationMS": 8.1527, "detail": "" } },
{ "pid": 1, "tid": 1, "ts": 36826345.6, "dur": 1625, "ph": "X", "name": "Metadata Strings", "args": { "durationMS": 1.625, "detail": "" } },
{ "pid": 1, "tid": 1, "ts": 36827977.6, "dur": 5772.8, "ph": "X", "name": "Events", "args": { "durationMS": 5.7728, "detail": "" } },
{ "pid": 1, "tid": 1, "ts": 36833753.6, "dur": 14403.8, "ph": "X", "name": "Properties", "args": { "durationMS": 14.4038, "detail": "" } },
{ "pid": 1, "tid": 1, "ts": 36848169.6, "dur": 122718.7, "ph": "X", "name": "Methods", "args": { "durationMS": 122.7187, "detail": "" } },
{ "pid": 1, "tid": 1, "ts": 36970902.4, "dur": 3566.7, "ph": "X", "name": "Parameter Default Values", "args": { "durationMS": 3.5667, "detail": "" } },
{ "pid": 1, "tid": 1, "ts": 36974473.6, "dur": 4746.2, "ph": "X", "name": "Field Default Values", "args": { "durationMS": 4.7462, "detail": "" } },
{ "pid": 1, "tid": 1, "ts": 36979232, "dur": 396.6, "ph": "X", "name": "Field and Parameter Default Values Data", "args": { "durationMS": 0.3966, "detail": "" } },
{ "pid": 1, "tid": 1, "ts": 36979638.4, "dur": 857.7, "ph": "X", "name": "Field Marshaled Sizes", "args": { "durationMS": 0.8577, "detail": "" } },
{ "pid": 1, "tid": 1, "ts": 36980505.6, "dur": 28923.5, "ph": "X", "name": "Parameters", "args": { "durationMS": 28.9235, "detail": "" } },
{ "pid": 1, "tid": 1, "ts": 37009440, "dur": 15256.2, "ph": "X", "name": "Fields", "args": { "durationMS": 15.2562, "detail": "" } },
{ "pid": 1, "tid": 1, "ts": 37024704, "dur": 3587.8, "ph": "X", "name": "Generic Parameters", "args": { "durationMS": 3.5878, "detail": "" } },
{ "pid": 1, "tid": 1, "ts": 37028297.6, "dur": 1180.8, "ph": "X", "name": "Generic Parameter Constraints", "args": { "durationMS": 1.1808, "detail": "" } },
{ "pid": 1, "tid": 1, "ts": 37029488, "dur": 4825, "ph": "X", "name": "Generic Containers", "args": { "durationMS": 4.825, "detail": "" } },
{ "pid": 1, "tid": 1, "ts": 37034774.4, "dur": 2923.6, "ph": "X", "name": "VTables", "args": { "durationMS": 2.9236, "detail": "" } },
{ "pid": 1, "tid": 1, "ts": 37037705.6, "dur": 1461.4, "ph": "X", "name": "Interface Offsets", "args": { "durationMS": 1.4614, "detail": "" } },
{ "pid": 1, "tid": 1, "ts": 37039177.6, "dur": 75670.7, "ph": "X", "name": "Type Definitions", "args": { "durationMS": 75.6707, "detail": "" } },
{ "pid": 1, "tid": 1, "ts": 37114860.8, "dur": 6464.3, "ph": "X", "name": "Images", "args": { "durationMS": 6.4643, "detail": "" } },
{ "pid": 1, "tid": 1, "ts": 37121331.2, "dur": 3851.9, "ph": "X", "name": "Assemblies", "args": { "durationMS": 3.8519, "detail": "" } },
{ "pid": 1, "tid": 1, "ts": 37125187.2, "dur": 1379.6, "ph": "X", "name": "Metadata Usage Lists", "args": { "durationMS": 1.3796, "detail": "" } },
{ "pid": 1, "tid": 1, "ts": 37126572.8, "dur": 5884.1, "ph": "X", "name": "Metadata Usage Pairs", "args": { "durationMS": 5.8841, "detail": "" } },
{ "pid": 1, "tid": 1, "ts": 37132707.2, "dur": 537.1, "ph": "X", "name": "Referenced Assemblies", "args": { "durationMS": 0.5371, "detail": "" } },
{ "pid": 1, "tid": 1, "ts": 37133248, "dur": 1268.7, "ph": "X", "name": "Attribute Types Ranges", "args": { "durationMS": 1.2687, "detail": "" } },
{ "pid": 1, "tid": 1, "ts": 37134521.6, "dur": 498.9, "ph": "X", "name": "Attribute Types", "args": { "durationMS": 0.4989, "detail": "" } },
{ "pid": 1, "tid": 1, "ts": 37135200, "dur": 546.3, "ph": "X", "name": "Unresolved Virtual Call Parameter Ranges", "args": { "durationMS": 0.5463, "detail": "" } },
{ "pid": 1, "tid": 1, "ts": 37135904, "dur": 3864.6, "ph": "X", "name": "Exported Types", "args": { "durationMS": 3.8646, "detail": "" } },
{ "pid": 1, "tid": 1, "ts": 37142403.2, "dur": 674, "ph": "X", "name": "CompletionPhase", "args": { "durationMS": 0.674, "detail": "" } }
],
"meta_datetime": "08/27/2020 20:46:53",
"meta_command_line": "/Applications/Unity/Hub/Editor/2020.1.0b2/Unity.app/Contents/il2cpp/build/deploy/net471/il2cpp.exe --convert-to-cpp --emit-null-checks --enable-array-bounds-check --dotnetprofile=unityaot --incremental-g-c-time-slice=3 --avoid-dynamic-library-copy --profiler-report --map-file-parser=/Applications/Unity/Hub/Editor/2020.1.0b2/Unity.app/Contents/Tools/MapFileParser/MapFileParser \"--directory=/Users/mm/Desktop/Gravity Balls/Temp/StagingArea/Data/Managed\" \"--generatedcppdir=/Users/mm/Desktop/Gravity Balls/Temp/il2cppOutput/il2cppOutput\"",
"meta_command_line_args": "/Applications/Unity/Hub/Editor/2020.1.0b2/Unity.app/Contents/il2cpp/build/deploy/net471/il2cpp.exe --convert-to-cpp --emit-null-checks --enable-array-bounds-check --dotnetprofile=unityaot --incremental-g-c-time-slice=3 --avoid-dynamic-library-copy --profiler-report --map-file-parser=/Applications/Unity/Hub/Editor/2020.1.0b2/Unity.app/Contents/Tools/MapFileParser/MapFileParser --directory=/Users/mm/Desktop/Gravity Balls/Temp/StagingArea/Data/Managed --generatedcppdir=/Users/mm/Desktop/Gravity Balls/Temp/il2cppOutput/il2cppOutput",
"meta_user_name": "mm",
"meta_os_version": "Unix 19.6.0.0",
"meta_cpu_count": "4"}
